{
	"EditRecord": {
		"Code": "",
		"TransType": "0",
		"TransNo": "",
		"DraftNo": "",
		"TransactionDate": "",
		"BPCode": "",
		"BPName": "",
		"PostingDate": "",
		"MarkupType": "0",
		"IssueBU": "",
		"ReceiveBU": "",
		"Remarks": "",
		"Requestor": "",
		"Status": "",
		"BPCodeDisabled": true,
		"BPNameDisabled": true,
		"ReceiveBUDisabled": true,
		"DocumentLines":[]
	},
	"AllItems": [{
		"ItemCode": "",
		"ItemDescription": ""
	}],
	"Pricing": [{
		"PriceList": "",
		"MarketPrice": ""
	}],

	"AllWarehouses": [{
		"WhsCode": "",
		"WhsName": ""
	}],

	"AllMarkupTypes": [{
		"key": "1",
		"value": "Percent"
	}, {
		"key": "2",
		"value": "Amount"
	}],

	"AllTransactionTypes": [{
			"key": "1",
			"value": "1 - Intra Org - Transfer"
		}, {
			"key": "2",
			"value": "2 - Inter Affiliates - Issue"
		}, {
			"key": "3",
			"value": "3 - Inter Affiliates - Receipt"
		}, {
			"key": "4",
			"value": "4 - RE - Electricity Transfer"
		}
	],
	"SelectedTransType": {
		"TransactionType": "0"
	}
}
